odoo8_addon_business_requirement_deliverable_default-8.0.2.0.2.99.dev3-py2.7-nspkg.pth
odoo8_addon_business_requirement_deliverable_default-8.0.2.0.2.99.dev3.dist-info/DESCRIPTION.rst
odoo8_addon_business_requirement_deliverable_default-8.0.2.0.2.99.dev3.dist-info/METADATA
odoo8_addon_business_requirement_deliverable_default-8.0.2.0.2.99.dev3.dist-info/RECORD
odoo8_addon_business_requirement_deliverable_default-8.0.2.0.2.99.dev3.dist-info/WHEEL
odoo8_addon_business_requirement_deliverable_default-8.0.2.0.2.99.dev3.dist-info/metadata.json
odoo8_addon_business_requirement_deliverable_default-8.0.2.0.2.99.dev3.dist-info/namespace_packages.txt
odoo8_addon_business_requirement_deliverable_default-8.0.2.0.2.99.dev3.dist-info/top_level.txt
odoo_addons/business_requirement_deliverable_default/README.rst
odoo_addons/business_requirement_deliverable_default/__init__.py
odoo_addons/business_requirement_deliverable_default/__openerp__.py
odoo_addons/business_requirement_deliverable_default/i18n/sl.po
odoo_addons/business_requirement_deliverable_default/models/__init__.py
odoo_addons/business_requirement_deliverable_default/models/business_requirement_deliverable_default.py
odoo_addons/business_requirement_deliverable_default/static/description/icon.png
odoo_addons/business_requirement_deliverable_default/static/img/bus_req_default.png
odoo_addons/business_requirement_deliverable_default/static/img/bus_req_default2.png
odoo_addons/business_requirement_deliverable_default/tests/__init__.py
odoo_addons/business_requirement_deliverable_default/tests/test_default_resources_from_product.py
odoo_addons/business_requirement_deliverable_default/views/business_requirement_deliverable_default.xml
